gmail_dev/__init__.py
gmail_dev/api_client.py
gmail_dev/api_response.py
gmail_dev/configuration.py
gmail_dev/exceptions.py
gmail_dev/py.typed
gmail_dev/rest.py
gmail_dev/api/__init__.py
gmail_dev/api/users_api.py
gmail_dev/models/__init__.py
gmail_dev/models/auto_forwarding.py
gmail_dev/models/batch_delete_messages_request.py
gmail_dev/models/batch_modify_messages_request.py
gmail_dev/models/delegate.py
gmail_dev/models/draft.py
gmail_dev/models/filter.py
gmail_dev/models/filter_action.py
gmail_dev/models/filter_criteria.py
gmail_dev/models/forwarding_address.py
gmail_dev/models/history.py
gmail_dev/models/history_label_added.py
gmail_dev/models/history_label_removed.py
gmail_dev/models/history_message_added.py
gmail_dev/models/history_message_deleted.py
gmail_dev/models/imap_settings.py
gmail_dev/models/label.py
gmail_dev/models/label_color.py
gmail_dev/models/language_settings.py
gmail_dev/models/list_delegates_response.py
gmail_dev/models/list_drafts_response.py
gmail_dev/models/list_filters_response.py
gmail_dev/models/list_forwarding_addresses_response.py
gmail_dev/models/list_history_response.py
gmail_dev/models/list_labels_response.py
gmail_dev/models/list_messages_response.py
gmail_dev/models/list_send_as_response.py
gmail_dev/models/list_smime_info_response.py
gmail_dev/models/list_threads_response.py
gmail_dev/models/message.py
gmail_dev/models/message_part.py
gmail_dev/models/message_part_body.py
gmail_dev/models/message_part_header.py
gmail_dev/models/modify_message_request.py
gmail_dev/models/modify_thread_request.py
gmail_dev/models/pop_settings.py
gmail_dev/models/profile.py
gmail_dev/models/send_as.py
gmail_dev/models/smime_info.py
gmail_dev/models/smtp_msa.py
gmail_dev/models/thread.py
gmail_dev/models/vacation_settings.py
gmail_dev/models/watch_request.py
gmail_dev/models/watch_response.py
gmail_dev-0.0.1.dist-info/METADATA
gmail_dev-0.0.1.dist-info/WHEEL
gmail_dev-0.0.1.dist-info/top_level.txt
gmail_dev-0.0.1.dist-info/RECORD
